MtxDrawer/Drawer.py
MtxDrawer/MtxReader.cpython-311-darwin.so
MtxDrawer/__init__.py
MtxDrawer/main.py
MtxDrawer-0.0.32.dist-info/LICENSE
MtxDrawer-0.0.32.dist-info/METADATA
MtxDrawer-0.0.32.dist-info/WHEEL
MtxDrawer-0.0.32.dist-info/entry_points.txt
MtxDrawer-0.0.32.dist-info/top_level.txt
MtxDrawer-0.0.32.dist-info/zip-safe
MtxDrawer-0.0.32.dist-info/RECORD
