Metadata-Version: 2.1
Name: MtxDrawer
Version: 0.0.32
Summary: Draw Mtx As Thumbnail
Home-page: https://github.com/Rhythmicc/DrawMtxAsThumbnail
Author: RhythmLian
Author-email: RhythmLian@outlook.com
License: MIT
Classifier: Programming Language :: Python :: 3
Classifier: License :: OSI Approved :: MIT License
Classifier: Operating System :: OS Independent
License-File: LICENSE
Requires-Dist: numpy
Requires-Dist: matplotlib
Requires-Dist: Qpro
